brasser/__init__.py
brasser/brasser.py
brasser-1.0.5.dist-info/LICENSE
brasser-1.0.5.dist-info/METADATA
brasser-1.0.5.dist-info/WHEEL
brasser-1.0.5.dist-info/top_level.txt
brasser-1.0.5.dist-info/RECORD
