Metadata-Version: 2.1
Name: brasser
Version: 1.0.5
Summary: A library for generating cryptographically random UUIDs
Author: Bernward Sanchez
Author-email: contact@bern.codes
Classifier: Programming Language :: Python :: 3
Classifier: License :: OSI Approved :: MIT License
Classifier: Operating System :: OS Independent
License-File: LICENSE
